GnDocTrans/__init__.py
GnDocTrans/trace_profile.py
GnDocTrans/tri_derive_tile.py
GnDocTrans-0.0.5.dist-info/METADATA
GnDocTrans-0.0.5.dist-info/WHEEL
GnDocTrans-0.0.5.dist-info/top_level.txt
GnDocTrans-0.0.5.dist-info/RECORD
