Metadata-Version: 2.1
Name: GnDocTrans
Version: 0.0.5
Summary: UNKNOWN
Home-page: UNKNOWN
Author: 
Author-email: 
License: MIT
Keywords: doc,document
Platform: UNKNOWN
Classifier: Programming Language :: Python :: 3
Classifier: License :: OSI Approved :: MIT License
Classifier: Operating System :: OS Independent
Requires-Python: >=3.10,<3.11
Requires-Dist: numpy
Requires-Dist: opencv-python
